sqwool/__future_bunde.fpy
sqwool/__init__.py
sqwool/core.py
sqwool/extensions/linux-arm64/sqlean-linux-arm64/crypto.so
sqwool/extensions/linux-arm64/sqlean-linux-arm64/define.so
sqwool/extensions/linux-arm64/sqlean-linux-arm64/fileio.so
sqwool/extensions/linux-arm64/sqlean-linux-arm64/fuzzy.so
sqwool/extensions/linux-arm64/sqlean-linux-arm64/ipaddr.so
sqwool/extensions/linux-arm64/sqlean-linux-arm64/math.so
sqwool/extensions/linux-arm64/sqlean-linux-arm64/regexp.so
sqwool/extensions/linux-arm64/sqlean-linux-arm64/sqlean.so
sqwool/extensions/linux-arm64/sqlean-linux-arm64/stats.so
sqwool/extensions/linux-arm64/sqlean-linux-arm64/text.so
sqwool/extensions/linux-arm64/sqlean-linux-arm64/time.so
sqwool/extensions/linux-arm64/sqlean-linux-arm64/unicode.so
sqwool/extensions/linux-arm64/sqlean-linux-arm64/uuid.so
sqwool/extensions/linux-arm64/sqlean-linux-arm64/vsv.so
sqwool/extensions/linux-arm64/sqlite_vec-linux-arm64/vec0.so
sqwool/extensions/linux-x86/sqlean-linux-x86/crypto.so
sqwool/extensions/linux-x86/sqlean-linux-x86/define.so
sqwool/extensions/linux-x86/sqlean-linux-x86/fileio.so
sqwool/extensions/linux-x86/sqlean-linux-x86/fuzzy.so
sqwool/extensions/linux-x86/sqlean-linux-x86/ipaddr.so
sqwool/extensions/linux-x86/sqlean-linux-x86/math.so
sqwool/extensions/linux-x86/sqlean-linux-x86/regexp.so
sqwool/extensions/linux-x86/sqlean-linux-x86/sqlean.so
sqwool/extensions/linux-x86/sqlean-linux-x86/stats.so
sqwool/extensions/linux-x86/sqlean-linux-x86/text.so
sqwool/extensions/linux-x86/sqlean-linux-x86/time.so
sqwool/extensions/linux-x86/sqlean-linux-x86/unicode.so
sqwool/extensions/linux-x86/sqlean-linux-x86/uuid.so
sqwool/extensions/linux-x86/sqlean-linux-x86/vsv.so
sqwool/extensions/linux-x86/sqlite_vec-linux-x86/vec0.so
sqwool/extensions/macos-arm64/sqlean-macos-arm64/crypto.dylib
sqwool/extensions/macos-arm64/sqlean-macos-arm64/define.dylib
sqwool/extensions/macos-arm64/sqlean-macos-arm64/fileio.dylib
sqwool/extensions/macos-arm64/sqlean-macos-arm64/fuzzy.dylib
sqwool-0.1.2.dist-info/METADATA
sqwool-0.1.2.dist-info/WHEEL
sqwool-0.1.2.dist-info/top_level.txt
sqwool-0.1.2.dist-info/RECORD
