Metadata-Version: 2.1
Name: sqwool
Version: 0.1.2
Summary: My package description
Author-email: James AMD <***@gmail.com>
License: BSD-3-Clause
Classifier: Programming Language :: Python :: 3
Requires-Python: >=3.8
